Workbook

Sheet Inputs
A1: Lumen Retail Group - assumptions | B1: Value
A2: Enterprise revenue, base year ($k) | B2: 34900
A3: Mid-market revenue, base year ($k) | B3: 17500
A4: SMB revenue, base year ($k) | B4: 11850
A5: Enterprise annual growth | B5: 0.12
A6: Mid-market annual growth | B6: 0.04
A7: SMB annual growth | B7: 0.06
A8: Gross margin | B8: 0.71
A9: Operating expenses (% of revenue) | B9: 0.15
A10: D&A (% of revenue) | B10: 0.05
A11: Tax rate (on EBIT) | B11: 0.21
A12: Capex (% of revenue) | B12: 0.06
A13: Net working capital (% of revenue) | B13: 0.06
... A17: Diluted shares outstanding (k) | B17: 29500

Sheet Revenue
A1: Revenue build ($k) | B1: Base | C1: Year 1 | D1: Year 2 | E1: Year 3 | F1: Year 4 | G1: Year 5
A2: Enterprise | B2: =Inputs!$B$2 | C2: =B2*(1+Inputs!$B$5) | D2: =C2*(1+Inputs!$B$5) | E2: =D2*(1+Inputs!$B$5) | F2: =D2*(1+Inputs!$B$5) | G2: =F2*(1+Inputs!$B$5)
A3: Mid-market | B3: =Inputs!$B$3 | C3: =B3*(1+Inputs!$B$6) | D3: =C3*(1+Inputs!$B$6) | E3: =D3*(1+Inputs!$B$6) | F3: =E3*(1+Inputs!$B$6) | G3: =F3*(1+Inputs!$B$6)
A4: SMB | B4: =Inputs!$B$4 | C4: =B4*(1+Inputs!$B$7) | D4: =C4*(1+Inputs!$B$7) | E4: =D4*(1+Inputs!$B$7) | F4: =E4*(1+Inputs!$B$7) | G4: =F4*(1+Inputs!$B$7)
A5: Total revenue | B5: =SUM(B2:B4) | C5: =SUM(C2:C4) | D5: =SUM(D2:D4) | E5: =SUM(E2:E4) | F5: =SUM(F2:F4) | G5: =SUM(G2:G4)

Sheet PnL
A1: Income statement ($k) | B1: Base | C1: Year 1 | D1: Year 2 | E1: Year 3 | F1: Year 4 | G1: Year 5
A2: Revenue | B2: =Revenue!B5 | C2: =Revenue!C5 | D2: =Revenue!D5 | E2: =Revenue!E4 | F2: =Revenue!F5 | G2: =Revenue!G5
A3: COGS | C3: =C2*(1-Inputs!$B$8) | D3: =D2*(1-Inputs!$B$8) | E3: =E2*(1-Inputs!$B$8) | F3: =F2*(1-Inputs!$B$8) | G3: 25128
A4: Gross profit | C4: =C2-C3 | D4: =D2-D3 | E4: =E2-E3 | F4: =F2-F3 | G4: =G2-G3
A5: Operating expenses | C5: =C2*Inputs!$B$9 | D5: =D2*Inputs!$B$9 | E5: =E2*Inputs!$B$9 | F5: =F2*Inputs!$B$9 | G5: =G2*Inputs!$B$9
A6: EBITDA | C6: =C4-C5 | D6: =D4-D5 | E6: =E4-E5 | F6: =F4-F5 | G6: =G4-G5
A7: D&A | C7: =C2*Inputs!$B$10 | D7: =D2*Inputs!$B$10 | E7: =E2*Inputs!$B$10 | F7: =F2*Inputs!$B$10 | G7: =G2*Inputs!$B$10
A8: EBIT | C8: =C6-C7 | D8: =D6-D7 | E8: =E6-E7 | F8: =F6-F7 | G8: =G6-G7
A9: Tax | C9: =C8*Inputs!$B$11 | D9: =D8*Inputs!$B$11 | E9: =E6*Inputs!$B$11 | F9: =F8*Inputs!$B$11 | G9: =G8*Inputs!$B$11
A10: NOPAT | C10: =C8-C9 | D10: =D8-D9 | E10: =E8-E9 | F10: =F8-F9 | G10: =G8-G9

Sheet CashFlow
A1: Unlevered free cash flow ($k) | B1: Base | C1: Year 1 | D1: Year 2 | E1: Year 3 | F1: Year 4 | G1: Year 5
A2: NOPAT | C2: =PnL!C10 | D2: =PnL!D10 | E2: =PnL!E10 | F2: =PnL!F10 | G2: =PnL!G10
A3: Add: D&A | C3: =PnL!C7 | D3: =PnL!D7 | E3: =PnL!E7 | F3: =PnL!F7 | G3: =PnL!G7
A4: Less: capex | C4: =PnL!C2*Inputs!$B$12 | D4: =PnL!D2*Inputs!$B$12 | E4: =PnL!E2*Inputs!$B$12 | F4: =PnL!F2*Inputs!$B$12 | G4: =PnL!G2*Inputs!$B$12
A5: Net working capital | B5: =PnL!B2*Inputs!$B$13 | C5: =PnL!C2*Inputs!$B$13 | D5: =PnL!D2*Inputs!$B$13 | E5: =PnL!E2*Inputs!$B$13 | F5: =PnL!F2*Inputs!$B$13 | G5: =PnL!G2*Inputs!$B$13
A6: Less: increase in NWC | C6: =C5-B5 | D6: =D5-C5 | E6: =E5-D5 | F6: =F5-E5 | G6: =G5-F5
A7: Unlevered FCF | C7: =C2+C3-C4-C6 | D7: =D2+D3-D4-D6 | E7: =E2+E3-E4-E6 | F7: =F2+F3-F4-F6 | G7: =G2+G3-G4-G6

Sheet DCF
A1: Discounted cash flow | B1: Base | C1: Year 1 | D1: Year 2 | E1: Year 3 | F1: Year 4 | G1: Year 5
A2: Period | C2: 1 | D2: 2 | E2: 3 | F2: 4 | G2: 5
A3: Discount factor | C3: =1/(1+Inputs!$B$14)^C2 | D3: =1/(1+Inputs!$B$14)^D2 | E3: =1/(1+Inputs!$B$14)^E2 | F3: =1/(1+Inputs!$B$14)^F2 | G3: =1/(1+Inputs!$B$14)^G2
A4: PV of FCF | C4: =CashFlow!C7*C3 | D4: =CashFlow!D7*D3 | E4: =CashFlow!E7*E3 | F4: =CashFlow!F7*F3 | G4: =CashFlow!G7*G3
A6: Sum of PV of FCF | B6: =SUM(C4:G4)
A7: Terminal value (Gordon growth, at Year 5) | B7: =CashFlow!G7*(1+Inputs!$B$15)/(Inputs!$B$14-Inputs!$B$15)
A8: PV of terminal value | B8: =B7
A9: Enterprise value | B9: =B6+B8
A10: Equity value | B10: =B9-Inputs!$B$16
A11: Equity value per share ($) | B11: =B10/Inputs!$B$17

Sheet Notes
A1: MODEL SPECIFICATION - Lumen Retail Group
A2: All money in $ thousands. Column B is the base year; C..G are forecast years 1-5.
A3: Every assumption lives on Inputs (one value per line, percentages stored as decimals, e.g. 25% = 0.25).
A4: No other sheet should contain hard-coded numbers except DCF row 2 (period numbers 1..5).
A6: ASSUMPTIONS (signed off by the deal team):
A7: Inputs!B2 Enterprise revenue, base year ($k) = 34,900
A8: Inputs!B3 Mid-market revenue, base year ($k) = 17,500
A9: Inputs!B4 SMB revenue, base year ($k) = 11,850
A10: Inputs!B5 Enterprise annual growth = 12%
A11: Inputs!B6 Mid-market annual growth = 4%
A12: Inputs!B7 SMB annual growth = 6%
A13: Inputs!B8 Gross margin = 71%
... A37: Equity value = EV - net debt. Per share = equity value / diluted shares.
